pymultifit/__init__.py
pymultifit/version.py
pymultifit/distributions/__init__.py
pymultifit/distributions/arcSine_d.py
pymultifit/distributions/betaPrime_d.py
pymultifit/distributions/beta_d.py
pymultifit/distributions/chiSquare_d.py
pymultifit/distributions/exponential_d.py
pymultifit/distributions/foldedNormal_d.py
pymultifit/distributions/gamma_d.py
pymultifit/distributions/gaussian_d.py
pymultifit/distributions/halfNormal_d.py
pymultifit/distributions/johnsonSU_d.py
pymultifit/distributions/laplace_d.py
pymultifit/distributions/logNormal_d.py
pymultifit/distributions/skewNormal_d.py
pymultifit/distributions/uniform_d.py
pymultifit/distributions/utilities_d.py
pymultifit/distributions/backend/__init__.py
pymultifit/distributions/backend/baseDistribution.py
pymultifit/distributions/backend/errorHandling.py
pymultifit/distributions/backend/polynomial_d.py
pymultifit/distributions/generalized/__init__.py
pymultifit/distributions/generalized/genNorm_d.py
pymultifit/distributions/generalized/scaledInvChiSquare_d.py
pymultifit/fitters/__init__.py
pymultifit/fitters/chiSquare_f.py
pymultifit/fitters/exponential_f.py
pymultifit/fitters/foldedNormal_f.py
pymultifit/fitters/gamma_f.py
pymultifit/fitters/gaussian_f.py
pymultifit/fitters/halfNormal_f.py
pymultifit/fitters/laplace_f.py
pymultifit/fitters/logNormal_f.py
pymultifit/fitters/mixed_f.py
pymultifit/fitters/polynomial_f.py
pymultifit/fitters/skewNormal_f.py
pymultifit/fitters/utilities_f.py
pymultifit/fitters/backend/__init__.py
pymultifit/fitters/backend/baseFitter.py
pymultifit/generators/__init__.py
pymultifit/generators/generators.py
pymultifit-1.0.9.dist-info/licenses/LICENSE
pymultifit-1.0.9.dist-info/METADATA
pymultifit-1.0.9.dist-info/WHEEL
pymultifit-1.0.9.dist-info/top_level.txt
pymultifit-1.0.9.dist-info/RECORD
