Metadata-Version: 2.4
Name: pymultifit
Version: 1.0.9
Summary: A library to fit data with multiple fitters.
Author-email: Syed Ali Mohsin Bukhari <syedali.b@outlook.com>
Project-URL: Homepage, https://readthedocs.pymultifit.com
Project-URL: Issues, https://github.com/syedalimohsinbukhari/pymultifit/issues
Project-URL: Repository, https://github.com/syedalimohsinbukhari/pyMultiFit/
Keywords: fitting,multi-modal,gaussian,lognormal,skew,curve fitting,scipy
Classifier: Development Status :: 5 - Production/Stable
Classifier: Intended Audience :: Science/Research
Classifier: Operating System :: OS Independent
Classifier: Programming Language :: Python :: 3.9
Classifier: Programming Language :: Python :: 3.10
Classifier: Programming Language :: Python :: 3.11
Classifier: Topic :: Scientific/Engineering :: Astronomy
Classifier: Topic :: Scientific/Engineering :: Mathematics
Classifier: Topic :: Scientific/Engineering :: Physics
Requires-Python: >=3.9
License-File: LICENSE
Requires-Dist: numpy<2.1.0
Requires-Dist: matplotlib
Requires-Dist: scipy
Requires-Dist: custom-inherit
Requires-Dist: mpyez
Provides-Extra: dev
Requires-Dist: pytest; extra == "dev"
Requires-Dist: seaborn; extra == "dev"
Requires-Dist: pandas; extra == "dev"
Requires-Dist: statsmodels; extra == "dev"
Requires-Dist: astropy; extra == "dev"
Requires-Dist: jupyter; extra == "dev"
Requires-Dist: notebook; extra == "dev"
Requires-Dist: build; extra == "dev"
Requires-Dist: memory_profiler; extra == "dev"
Requires-Dist: sphinx; extra == "dev"
Requires-Dist: sphinx-rtd-theme; extra == "dev"
Requires-Dist: pydata-sphinx-theme; extra == "dev"
Requires-Dist: sphinx-copybutton; extra == "dev"
Requires-Dist: sphinxcontrib-napoleon; extra == "dev"
Requires-Dist: numpydoc; extra == "dev"
Requires-Dist: nbsphinx; extra == "dev"
Requires-Dist: nbsphinx-link; extra == "dev"
Requires-Dist: sphinx-gallery; extra == "dev"
Requires-Dist: sphinx-autobuild; extra == "dev"
Requires-Dist: black; extra == "dev"
Requires-Dist: mypy; extra == "dev"
Dynamic: license-file
